./PKG-INFO
./README.md
./main.py
./pyproject.toml
./requirements.txt
./server.py
./setup.py
./youtrack_api.py
youtrack_mcp-0.2.0.dist-info/METADATA
youtrack_mcp-0.2.0.dist-info/WHEEL
youtrack_mcp-0.2.0.dist-info/RECORD
