Metadata-Version: 2.4
Name: youtrack-mcp
Version: 0.2.0
Summary: YouTrack MCP Server for Model Context Protocol
Project-URL: Homepage, https://github.com/av-frox/youtrack-mcp
Author-email: Aleksej Vasilev <a.vasilev@frox-it.de>
License-Expression: MIT
Requires-Python: >=3.10
Requires-Dist: mcp>=0.1.0
Requires-Dist: youtrack>=0.1.69
